butinfom/__init__.py
butinfom/calculmod.py
butinfom/chiffresym.py
butinfom/divisibilite.py
butinfom/numeration.py
butinfom/pivotgauss.py
butinfom/polynome.py
butinfom/utilitaires.py
butinfom-0.1.3.dist-info/licenses/LICENSE
butinfom-0.1.3.dist-info/METADATA
butinfom-0.1.3.dist-info/WHEEL
butinfom-0.1.3.dist-info/top_level.txt
butinfom-0.1.3.dist-info/RECORD
