Metadata-Version: 2.4
Name: butinfom
Version: 0.1.3
Summary: Outils pour l'enseignement des maths en BUT d'informatique
Author-email: Matthieu Bensussan <matthieu.bensussan@gmail.com>
License-Expression: MIT
Classifier: Programming Language :: Python :: 3
Classifier: Operating System :: OS Independent
Requires-Python: >=3.9
License-File: LICENSE
Requires-Dist: typing_extensions
Requires-Dist: sympy
Dynamic: license-file
